jpkgchanger/__init__.py
jpkgchanger/jpkgchanger.py
jpkgchanger-0.0.1.dist-info/entry_points.txt
jpkgchanger-0.0.1.dist-info/LICENSE
jpkgchanger-0.0.1.dist-info/WHEEL
jpkgchanger-0.0.1.dist-info/METADATA
jpkgchanger-0.0.1.dist-info/RECORD
