Metadata-Version: 2.1
Name: jpkgchanger
Version: 0.0.1
Summary: Change java project package name!
Home-page: https://github.com/intermedia-net/jpkgchanger
Author: Alexey Nikitin
Author-email: anikitin@intermedia.net
Requires-Python: >=3.6
Classifier: License :: OSI Approved :: MIT License
Classifier: Programming Language :: Python :: 3
